README.md
setup.py
paftv/__init__.py
paftv/paftv.py
paftv/lib/__init__.py
paftv/lib/alitv.py
paftv/lib/filter.py
paftv10.egg-info/PKG-INFO
paftv10.egg-info/SOURCES.txt
paftv10.egg-info/dependency_links.txt
paftv10.egg-info/entry_points.txt
paftv10.egg-info/requires.txt
paftv10.egg-info/top_level.txt