Metadata-Version: 1.0
Name: paftv10
Version: 0.1.0
Summary: Visualization for PAF files using AliTV
Home-page: https://github.com/MoinSebi/paftv
Author: Sebastian Vorbrugg
Author-email: sebastian.vorbrugg@tuebingen.mpg.de
License: MIT
Platform: UNKNOWN
